LICENSE
README.md
setup.py
pydash2hls/__init__.py
pydash2hls/converter.py
pydash2hls/exceptions.py
pydash2hls.egg-info/PKG-INFO
pydash2hls.egg-info/SOURCES.txt
pydash2hls.egg-info/dependency_links.txt
pydash2hls.egg-info/requires.txt
pydash2hls.egg-info/top_level.txt
test/test.py